{
  "IcoMoonType": "selection",
  "icons": [
    {
      "icon": {
        "paths": [
          "M426 726l384-384-60-62-324 324-152-152-60 60zM512 86c236 0 426 190 426 426s-190 426-426 426-426-190-426-426 190-426 426-426z"
        ],
        "attrs": [],
        "isMulticolor": false,
        "isMulticolor2": false,
        "tags": [
          "check_circle"
        ],
        "defaultCode": 59500,
        "grid": 24
      },
      "attrs": [],
      "properties": {
        "order": 51,
        "ligatures": "check_circle",
        "id": 151,
        "prevSize": 24,
        "code": 59500,
        "name": "check_circle"
      },
      "setIdx": 0,
      "setId": 1,
      "iconIdx": 151
    },
    {
      "icon": {
        "paths": [
          "M554 554v-256h-84v256h84zM554 726v-86h-84v86h84zM512 86c236 0 426 190 426 426s-190 426-426 426-426-190-426-426 190-426 426-426z"
        ],
        "attrs": [],
        "isMulticolor": false,
        "isMulticolor2": false,
        "tags": [
          "error"
        ],
        "defaultCode": 57344,
        "grid": 24
      },
      "attrs": [],
      "properties": {
        "order": 48,
        "ligatures": "error",
        "id": 245,
        "prevSize": 24,
        "code": 57344,
        "name": "error"
      },
      "setIdx": 0,
      "setId": 1,
      "iconIdx": 245
    },
    {
      "icon": {
        "paths": [
          "M554 384v-86h-84v86h84zM554 726v-256h-84v256h84zM512 86c236 0 426 190 426 426s-190 426-426 426-426-190-426-426 190-426 426-426z"
        ],
        "attrs": [],
        "isMulticolor": false,
        "isMulticolor2": false,
        "tags": [
          "info"
        ],
        "defaultCode": 59534,
        "grid": 24
      },
      "attrs": [],
      "properties": {
        "order": 52,
        "ligatures": "info",
        "id": 400,
        "prevSize": 24,
        "code": 59534,
        "name": "info"
      },
      "setIdx": 0,
      "setId": 1,
      "iconIdx": 400
    },
    {
      "icon": {
        "paths": [
          "M512 662c82 0 150-68 150-150s-68-150-150-150-150 68-150 150 68 150 150 150zM830 554l90 70c8 6 10 18 4 28l-86 148c-6 10-16 12-26 8l-106-42c-22 16-46 32-72 42l-16 112c-2 10-10 18-20 18h-172c-10 0-18-8-20-18l-16-112c-26-10-50-24-72-42l-106 42c-10 4-20 2-26-8l-86-148c-6-10-4-22 4-28l90-70c-2-14-2-28-2-42s0-28 2-42l-90-70c-8-6-10-18-4-28l86-148c6-10 16-12 26-8l106 42c22-16 46-32 72-42l16-112c2-10 10-18 20-18h172c10 0 18 8 20 18l16 112c26 10 50 24 72 42l106-42c10-4 20-2 26 8l86 148c6 10 4 22-4 28l-90 70c2 14 2 28 2 42s0 28-2 42z"
        ],
        "attrs": [],
        "isMulticolor": false,
        "isMulticolor2": false,
        "tags": [
          "settings"
        ],
        "defaultCode": 59576,
        "grid": 24
      },
      "attrs": [],
      "properties": {
        "order": 19,
        "ligatures": "settings",
        "id": 664,
        "prevSize": 24,
        "code": 59576,
        "name": "settings"
      },
      "setIdx": 0,
      "setId": 1,
      "iconIdx": 664
    }
  ],
  "height": 1024,
  "metadata": {
    "name": "icomoon"
  },
  "preferences": {
    "showGlyphs": true,
    "showCodes": true,
    "showQuickUse": true,
    "showQuickUse2": true,
    "showSVGs": true,
    "fontPref": {
      "prefix": "icon-",
      "metadata": {
        "fontFamily": "icomoon"
      },
      "metrics": {
        "emSize": 1024,
        "baseline": 6.25,
        "whitespace": 50
      }
    },
    "imagePref": {
      "prefix": "icon-",
      "png": true,
      "useClassSelector": true,
      "color": 0,
      "bgColor": 16777215
    },
    "historySize": 100,
    "gridSize": 16
  }
}